ses_email_forwarding/__init__.py
ses_email_forwarding/py.typed
ses_email_forwarding/_jsii/__init__.py
ses_email_forwarding/_jsii/ses-email-forwarding@5.0.1.jsii.tgz
ses_email_forwarding-5.0.1.dist-info/LICENSE
ses_email_forwarding-5.0.1.dist-info/METADATA
ses_email_forwarding-5.0.1.dist-info/WHEEL
ses_email_forwarding-5.0.1.dist-info/top_level.txt
ses_email_forwarding-5.0.1.dist-info/RECORD
